railsutra/__init__.py
railsutra/_internals/station_data.py
railsutra/_internals/stations.py
railsutra/_internals/train_data.py
railsutra/_internals/trains.py
railsutra/_internals/utils.py
railsutra-0.3.0.dist-info/licenses/LICENSE
railsutra-0.3.0.dist-info/METADATA
railsutra-0.3.0.dist-info/WHEEL
railsutra-0.3.0.dist-info/top_level.txt
railsutra-0.3.0.dist-info/RECORD
