Metadata-Version: 2.4
Name: railsutra
Version: 0.3.0
Summary: Your gateway to real-time Indian Railways data powered by NTES.
Author-email: Avinash Gupta <avinash12231@gmail.com>
Maintainer-email: Avinash Gupta <avinash12231@gmail.com>
License: MIT
Project-URL: Homepage, https://github.com/AvinashGupta2004/railsutra
Requires-Python: >=3.8
License-File: LICENSE
Requires-Dist: requests
Requires-Dist: bs4
Requires-Dist: pandas
Requires-Dist: numpy
Dynamic: license-file
